authbox_setup_version/__init__.py
authbox_setup_version/_version.py
proj_authbox_setup_version/__init__.py
proj_authbox_setup_version/asgi.py
proj_authbox_setup_version/settings.py
proj_authbox_setup_version/urls.py
proj_authbox_setup_version/wsgi.py
authbox_setup_version-1.0.9.dist-info/LICENSE
authbox_setup_version-1.0.9.dist-info/METADATA
authbox_setup_version-1.0.9.dist-info/WHEEL
authbox_setup_version-1.0.9.dist-info/top_level.txt
authbox_setup_version-1.0.9.dist-info/RECORD
