Metadata-Version: 2.1
Name: authbox-setup-version
Version: 1.0.9
Summary: Read version variable from _version.py and make incremental version
Home-page: https://github.com/PROJECT-AUTHBOX/authbox_setup_version.git
Author: Iwan Setiawan
Author-email: suratiwan03@gmail.com
Keywords: project,version,incremental,setup,django,python
Classifier: License :: OSI Approved :: BSD License
Classifier: Intended Audience :: Developers
Classifier: Programming Language :: Python
Classifier: Programming Language :: Python :: 3
License-File: LICENSE
Requires-Dist: incremental
Requires-Dist: click
Requires-Dist: twisted
